{
  "type_description_msg": {
    "type_description": {
      "type_name": "flexbe_msgs/action/BehaviorSynthesis_SendGoal",
      "fields": [
        {
          "name": "request_message",
          "type": {
            "type_id": 1,
            "capacity": 0,
            "string_capacity": 0,
            "nested_type_name": "flexbe_msgs/action/BehaviorSynthesis_SendGoal_Request"
          },
          "default_value": ""
        },
        {
          "name": "response_message",
          "type": {
            "type_id": 1,
            "capacity": 0,
            "string_capacity": 0,
            "nested_type_name": "flexbe_msgs/action/BehaviorSynthesis_SendGoal_Response"
          },
          "default_value": ""
        },
        {
          "name": "event_message",
          "type": {
            "type_id": 1,
            "capacity": 0,
            "string_capacity": 0,
            "nested_type_name": "flexbe_msgs/action/BehaviorSynthesis_SendGoal_Event"
          },
          "default_value": ""
        }
      ]
    },
    "referenced_type_descriptions": [
      {
        "type_name": "builtin_interfaces/msg/Time",
        "fields": [
          {
            "name": "sec",
            "type": {
              "type_id": 6,
              "capacity": 0,
              "string_capacity": 0,
              "nested_type_name": ""
            },
            "default_value": ""
          },
          {
            "name": "nanosec",
            "type": {
              "type_id": 7,
              "capacity": 0,
              "string_capacity": 0,
              "nested_type_name": ""
            },
            "default_value": ""
          }
        ]
      },
      {
        "type_name": "flexbe_msgs/action/BehaviorSynthesis_Goal",
        "fields": [
          {
            "name": "request",
            "type": {
              "type_id": 1,
              "capacity": 0,
              "string_capacity": 0,
              "nested_type_name": "flexbe_msgs/msg/SynthesisRequest"
            },
            "default_value": ""
          }
        ]
      },
      {
        "type_name": "flexbe_msgs/action/BehaviorSynthesis_SendGoal_Event",
        "fields": [
          {
            "name": "info",
            "type": {
              "type_id": 1,
              "capacity": 0,
              "string_capacity": 0,
              "nested_type_name": "service_msgs/msg/ServiceEventInfo"
            },
            "default_value": ""
          },
          {
            "name": "request",
            "type": {
              "type_id": 97,
              "capacity": 1,
              "string_capacity": 0,
              "nested_type_name": "flexbe_msgs/action/BehaviorSynthesis_SendGoal_Request"
            },
            "default_value": ""
          },
          {
            "name": "response",
            "type": {
              "type_id": 97,
              "capacity": 1,
              "string_capacity": 0,
              "nested_type_name": "flexbe_msgs/action/BehaviorSynthesis_SendGoal_Response"
            },
            "default_value": ""
          }
        ]
      },
      {
        "type_name": "flexbe_msgs/action/BehaviorSynthesis_SendGoal_Request",
        "fields": [
          {
            "name": "goal_id",
            "type": {
              "type_id": 1,
              "capacity": 0,
              "string_capacity": 0,
              "nested_type_name": "unique_identifier_msgs/msg/UUID"
            },
            "default_value": ""
          },
          {
            "name": "goal",
            "type": {
              "type_id": 1,
              "capacity": 0,
              "string_capacity": 0,
              "nested_type_name": "flexbe_msgs/action/BehaviorSynthesis_Goal"
            },
            "default_value": ""
          }
        ]
      },
      {
        "type_name": "flexbe_msgs/action/BehaviorSynthesis_SendGoal_Response",
        "fields": [
          {
            "name": "accepted",
            "type": {
              "type_id": 15,
              "capacity": 0,
              "string_capacity": 0,
              "nested_type_name": ""
            },
            "default_value": ""
          },
          {
            "name": "stamp",
            "type": {
              "type_id": 1,
              "capacity": 0,
              "string_capacity": 0,
              "nested_type_name": "builtin_interfaces/msg/Time"
            },
            "default_value": ""
          }
        ]
      },
      {
        "type_name": "flexbe_msgs/msg/SynthesisRequest",
        "fields": [
          {
            "name": "name",
            "type": {
              "type_id": 17,
              "capacity": 0,
              "string_capacity": 0,
              "nested_type_name": ""
            },
            "default_value": ""
          },
          {
            "name": "system",
            "type": {
              "type_id": 17,
              "capacity": 0,
              "string_capacity": 0,
              "nested_type_name": ""
            },
            "default_value": ""
          },
          {
            "name": "goal",
            "type": {
              "type_id": 17,
              "capacity": 0,
              "string_capacity": 0,
              "nested_type_name": ""
            },
            "default_value": ""
          },
          {
            "name": "initial_condition",
            "type": {
              "type_id": 17,
              "capacity": 0,
              "string_capacity": 0,
              "nested_type_name": ""
            },
            "default_value": ""
          },
          {
            "name": "sm_outcomes",
            "type": {
              "type_id": 161,
              "capacity": 0,
              "string_capacity": 0,
              "nested_type_name": ""
            },
            "default_value": ""
          }
        ]
      },
      {
        "type_name": "service_msgs/msg/ServiceEventInfo",
        "fields": [
          {
            "name": "event_type",
            "type": {
              "type_id": 3,
              "capacity": 0,
              "string_capacity": 0,
              "nested_type_name": ""
            },
            "default_value": ""
          },
          {
            "name": "stamp",
            "type": {
              "type_id": 1,
              "capacity": 0,
              "string_capacity": 0,
              "nested_type_name": "builtin_interfaces/msg/Time"
            },
            "default_value": ""
          },
          {
            "name": "client_gid",
            "type": {
              "type_id": 51,
              "capacity": 16,
              "string_capacity": 0,
              "nested_type_name": ""
            },
            "default_value": ""
          },
          {
            "name": "sequence_number",
            "type": {
              "type_id": 8,
              "capacity": 0,
              "string_capacity": 0,
              "nested_type_name": ""
            },
            "default_value": ""
          }
        ]
      },
      {
        "type_name": "unique_identifier_msgs/msg/UUID",
        "fields": [
          {
            "name": "uuid",
            "type": {
              "type_id": 51,
              "capacity": 16,
              "string_capacity": 0,
              "nested_type_name": ""
            },
            "default_value": ""
          }
        ]
      }
    ]
  },
  "type_hashes": [
    {
      "type_name": "flexbe_msgs/action/BehaviorSynthesis_SendGoal",
      "hash_string": "RIHS01_7a03749d79441a6c289a6c431305a0e2eb61944e433db52a9b6da168c354e87d"
    },
    {
      "type_name": "builtin_interfaces/msg/Time",
      "hash_string": "RIHS01_b106235e25a4c5ed35098aa0a61a3ee9c9b18d197f398b0e4206cea9acf9c197"
    },
    {
      "type_name": "flexbe_msgs/action/BehaviorSynthesis_Goal",
      "hash_string": "RIHS01_18d105144ef57c635ee011a57d7907f2560fd8bca06ddd4f923ec589e3231131"
    },
    {
      "type_name": "flexbe_msgs/action/BehaviorSynthesis_SendGoal_Event",
      "hash_string": "RIHS01_54e7b88c0dcbefe9963960668e93ae74af3166e4df0b4de4fb2285cc3b70c587"
    },
    {
      "type_name": "flexbe_msgs/action/BehaviorSynthesis_SendGoal_Request",
      "hash_string": "RIHS01_f3a98beac2657b7ce8bae45abfd6b40342de8073ef031c06bcc17d7b47fb7355"
    },
    {
      "type_name": "flexbe_msgs/action/BehaviorSynthesis_SendGoal_Response",
      "hash_string": "RIHS01_361f59a49240350be22b1bab28331a032a3159354d84dcaeea7f37f78bb6760c"
    },
    {
      "type_name": "flexbe_msgs/msg/SynthesisRequest",
      "hash_string": "RIHS01_68707412094a236ea34aee9bb49f2eb142f2c4648f3bd2cead98f17bc4663adb"
    },
    {
      "type_name": "service_msgs/msg/ServiceEventInfo",
      "hash_string": "RIHS01_41bcbbe07a75c9b52bc96bfd5c24d7f0fc0a08c0cb7921b3373c5732345a6f45"
    },
    {
      "type_name": "unique_identifier_msgs/msg/UUID",
      "hash_string": "RIHS01_1b8e8aca958cbea28fe6ef60bf6c19b683c97a9ef60bb34752067d0f2f7ab437"
    }
  ]
}